amygda/__init__.py
amygda/core.py
amygda-1.3.2.data/scripts/analyse-plate-with-amygda.py
config/CHNMCMM2-conc-matrix.txt
config/CHNMCMM2-dilution-matrix.txt
config/CHNMCMM2-drug-matrix.txt
config/GB1ECSDP-conc-matrix.txt
config/GB1ECSDP-dilution-matrix.txt
config/GB1ECSDP-drug-matrix.txt
config/GPALL1F-conc-matrix.txt
config/GPALL1F-dilution-matrix.txt
config/GPALL1F-drug-matrix.txt
config/UKMYC5-conc-matrix.txt
config/UKMYC5-dilution-matrix.txt
config/UKMYC5-drug-matrix.txt
config/UKMYC6-conc-matrix.txt
config/UKMYC6-dilution-matrix.txt
config/UKMYC6-drug-matrix.txt
tests/__init__.py
tests/test_core.py
amygda-1.3.2.dist-info/LICENCE.md
amygda-1.3.2.dist-info/METADATA
amygda-1.3.2.dist-info/WHEEL
amygda-1.3.2.dist-info/top_level.txt
amygda-1.3.2.dist-info/RECORD
