Metadata-Version: 2.1
Name: amygda
Version: 1.3.2
Summary: Measure the mycobacterial growth in a 96-well plate, thereby determining the MICs
Home-page: https://github.com/fowlerlab/amygda
Author: Philip W Fowler
License: University of Oxford License, see LICENSE
Keywords: AMR,TB,clinical microbiology,minimum inhibitory concentration,image processing
Classifier: Programming Language :: Python :: 3
License-File: LICENCE.md
Requires-Dist: numpy >=1.13
Requires-Dist: datreant >=1.0.2
Requires-Dist: opencv-python >=3.4
Requires-Dist: scipy >=1.1.0
Requires-Dist: matplotlib >=2.2.2
Requires-Dist: pytest >=7.1
Requires-Dist: pytest-cov
